weibo_crawler/__init__.py
weibo_crawler/comments.py
weibo_crawler/follow.py
weibo_crawler/profile.py
weibo_crawler/weibos.py
weibo_crawler-0.2.dist-info/METADATA
weibo_crawler-0.2.dist-info/WHEEL
weibo_crawler-0.2.dist-info/top_level.txt
weibo_crawler-0.2.dist-info/RECORD
