Metadata-Version: 2.1
Name: weibo-crawler
Version: 0.2
Summary: weibo_crawler 最简单的wiebo爬虫，可以轻度的进行微博数据采集
Home-page: https://github.com/thunderhit/weibo_crawler
Author: 大邓
Author-email: thunderhit@qq.com
License: MIT
Keywords: data collect,数据采集,weibo,微博
Platform: UNKNOWN
Requires-Python: >=3.5
Requires-Dist: requests
Requires-Dist: pyquery
